samesame/__init__.py
samesame/_bayesboot.py
samesame/_data.py
samesame/_stats.py
samesame/_utils.py
samesame/_wecdf.py
samesame/bayes.py
samesame/ctst.py
samesame/metrics.py
samesame/nit.py
samesame/py.typed
samesame-0.1.2.dist-info/WHEEL
samesame-0.1.2.dist-info/METADATA
samesame-0.1.2.dist-info/RECORD
