Metadata-Version: 2.3
Name: samesame
Version: 0.1.2
Summary: Classifier two-sample tests and noninferiority tests.
Keywords: drift detection,data monitoring,dataset shift,data validation,model validation,noninferiority tests,statistical tests
Author: Vathy M. Kamulete
Author-email: Vathy M. Kamulete <vathymut@gmail.com>
License:                    GNU LESSER GENERAL PUBLIC LICENSE
Classifier: Programming Language :: Python :: 3.12
Classifier: Programming Language :: Python :: 3.13
Classifier: Typing :: Typed
Classifier: Topic :: Scientific/Engineering
Classifier: Topic :: Scientific/Engineering :: Artificial Intelligence
Classifier: Intended Audience :: Science/Research
Classifier: Intended Audience :: Developers
Classifier: License :: OSI Approved :: GNU Lesser General Public License v3 (LGPLv3)
Classifier: Operating System :: OS Independent
Requires-Dist: numpy>=1.21
Requires-Dist: scipy>=1.15
Requires-Dist: scikit-learn
Requires-Dist: samesame[docs,test] ; extra == 'dev'
Requires-Dist: mkdocs-material ; extra == 'docs'
Requires-Dist: mkdocstrings-python ; extra == 'docs'
Requires-Dist: numpydoc ; extra == 'docs'
Requires-Dist: jupyter ; extra == 'docs'
Requires-Dist: uv ; extra == 'test'
Requires-Dist: pytest ; extra == 'test'
Requires-Dist: pytest-cov ; extra == 'test'
Requires-Dist: ruff ; extra == 'test'
Maintainer: Vathy M. Kamulete
Maintainer-email: Vathy M. Kamulete <vathymut@gmail.com>
Requires-Python: >=3.12
Provides-Extra: dev
Provides-Extra: docs
Provides-Extra: test
